[
    {
        "title": "katk1.dev",
        "badge": "Current",
        "desc": "The Bootstrap rewrite of this site, made only days after publishing the original from-scratch site",
        "link": "https://katk1.dev",
        "date": "April, 2024"
    },
    {
        "title": "taikopp.com",
        "badge": "Current",
        "desc": "A complete rewrite of the old versions of taikopp.com using Bootstrap",
        "link": "https://www.taikopp.com",
        "date": "April, 2024"
    },
    {
        "title": "katk1.dev v1",
        "badge": "Outdated",
        "desc": "The original version of this site, before I remade it using Bootstrap.",
        "link": "https://github.com/KatK1/katk1.dev/tree/0609b6996f1da4b3cc971645892e1dfc872c937c",
        "date": "April, 2024"
    },
    {
        "title": "taikopp.com v2",
        "badge": "Outdated",
        "desc": "Much the same website it had been, with a facelift",
        "link": "https://katk1.dev/legacy/taikopp",
        "date": "May, 2023"
    },
    {
        "title": "taikopp.com v1",
        "badge": "Outdated",
        "desc": "This is a simple website used for calculating how much a play would be worth in the popular rhythm game osu! (specifically, in the gamemode osu!taiko) at various points in time",
        "link": "https://github.com/KatK1/taikopp.com/tree/0d907841302e660d0b27441ac610aaa92e72b9c3",
        "date": "October, 2022"
    }
]
